persoonallisuus/__init__.py
persoonallisuus-2023.10.29.dist-info/LICENSE
persoonallisuus-2023.10.29.dist-info/METADATA
persoonallisuus-2023.10.29.dist-info/WHEEL
persoonallisuus-2023.10.29.dist-info/entry_points.txt
persoonallisuus-2023.10.29.dist-info/top_level.txt
persoonallisuus-2023.10.29.dist-info/RECORD
