Metadata-Version: 2.1
Name: persoonallisuus
Version: 2023.10.29
Summary: Personality (Finnish: persoonallisuus) - who am I currently and how should I behave?
Author-email: Stefan Hagen <stefan@hagen.link>
Maintainer-email: Stefan Hagen <stefan@hagen.link>
Project-URL: Homepage, https://git.sr.ht/~sthagen/persoonallisuus
Project-URL: Bug-Tracker, https://todo.sr.ht/~sthagen/persoonallisuus
Project-URL: Documentation, https://codes.dilettant.life/docs/persoonallisuus
Project-URL: Source-Code, https://git.sr.ht/~sthagen/persoonallisuus
Project-URL: Test-Coverage, https://codes.dilettant.life/coverage/persoonallisuus
Keywords: configuration,developer-tools
Classifier: Development Status :: 3 - Alpha
Classifier: Intended Audience :: Developers
Classifier: License :: OSI Approved :: MIT License
Classifier: Programming Language :: Python :: 3.10
Classifier: Programming Language :: Python :: 3.11
Classifier: Programming Language :: Python :: 3.12
Classifier: Programming Language :: Python :: 3.9
Requires-Python: >=3.9
License-File: LICENSE
Requires-Dist: PyYAML >=6.0.1
Requires-Dist: lxml >=4.9.3
Requires-Dist: msgspec >=0.18.4
Requires-Dist: rtoml >=0.9.0
Provides-Extra: dev
Requires-Dist: black ; extra == 'dev'
Requires-Dist: coverage ; extra == 'dev'
Requires-Dist: hypothesis ; extra == 'dev'
Requires-Dist: mypy ; extra == 'dev'
Requires-Dist: pytest ; extra == 'dev'
Requires-Dist: pytest-cov ; extra == 'dev'
Requires-Dist: pytest-flake8 ; extra == 'dev'
